tests/__init__.py
tests/test_edges.py
tests/test_graphs.py
tests/test_nodes.py
tests/test_trees.py
treefast/__init__.py
treefast/abc_module.py
treefast/binary_tree.py
treefast/edge.py
treefast/graph.py
treefast/node.py
treefast-0.2.0.dist-info/LICENSE
treefast-0.2.0.dist-info/METADATA
treefast-0.2.0.dist-info/WHEEL
treefast-0.2.0.dist-info/top_level.txt
treefast-0.2.0.dist-info/RECORD
