Metadata-Version: 2.1
Name: treefast
Version: 0.2.0
Summary: Библиотека для работы с гарфами
Home-page: https://github.com/ritatay635/treefast
Author: Станислав Тышко
Author-email: pol.dast.vid@gmail.com
Classifier: Programming Language :: Python :: 3
Classifier: License :: OSI Approved :: MIT License
Classifier: Operating System :: OS Independent
Requires-Python: >=3.6
License-File: LICENSE
Provides-Extra: dev
Requires-Dist: pytest ; extra == 'dev'
Requires-Dist: pytest-cov ; extra == 'dev'
Requires-Dist: black ; extra == 'dev'
Requires-Dist: flake8 ; extra == 'dev'
Requires-Dist: mypy ; extra == 'dev'
